[
  {
    "dates": [
      {
        "date": "15.03.2018"
      }
    ],
    "topic": "Blatt 1"
  },
  {
    "cancelled": true,
    "dates": [
      {
        "date": "22.03.2018"
      }
    ],
    "topic": "Blatt 1"
  },
  {
    "cancelled": true,
    "dates": [
      {
        "date": "29.03.2018"
      }
    ],
    "topic": "vorlesungsfrei (Ostern)"
  },
  {
    "dates": [
      {
        "date": "05.04.2018"
      }
    ],
    "topic": "Blatt 1 (Abgabe 11.04.2018, 08:00 Uhr)"
  },
  {
    "dates": [
      {
        "date": "12.04.2018"
      }
    ],
    "topic": "Blatt 2"
  },
  {
    "cancelled": true,
    "dates": [
      {
        "date": "19.04.2018"
      }
    ],
    "topic": "Blatt 2"
  },
  {
    "dates": [
      {
        "date": "26.04.2018"
      }
    ],
    "topic": "Blatt 2 (Abgabe 02.05.2018, 08:00 Uhr)"
  },
  {
    "dates": [
      {
        "date": "03.05.2018"
      }
    ],
    "topic": "Blatt 3"
  },
  {
    "cancelled": true,
    "dates": [
      {
        "date": "10.05.2018"
      }
    ],
    "topic": "vorlesungsfrei (Christi Himmelfahrt)"
  },
  {
    "dates": [
      {
        "date": "17.05.2018"
      }
    ],
    "topic": "Blatt 3 (Abgabe 23.05.2018, 08:00 Uhr)"
  },
  {
    "dates": [
      {
        "date": "24.05.2018"
      }
    ],
    "topic": "Blatt 4"
  },
  {
    "cancelled": true,
    "dates": [
      {
        "date": "31.05.2018"
      }
    ],
    "topic": "vorlesungsfrei (Fronleichnam)"
  },
  {
    "dates": [
      {
        "date": "07.06.2018"
      }
    ],
    "topic": "Blatt 4 (Abgabe 13.06.2018, 08:00 Uhr)"
  },
  {
    "dates": [
      {
        "date": "14.06.2018"
      }
    ],
    "topic": "Blatt 5"
  },
  {
    "dates": [
      {
        "date": "21.06.2018"
      }
    ],
    "topic": "Blatt 5 (Abgabe 27.06.2018, 08:00 Uhr)"
  },
  {
    "dates": [
      {
        "date": "28.06.2018"
      }
    ],
    "topic": "Fragestunde für die Klausur"
  }
]
